{
  "_class": "rectangle",
  "booleanOperation": 0,
  "clippingMaskMode": 0,
  "do_objectID": "733A5EDD-9CC6-47A5-A421-D03FC9757644",
  "edited": false,
  "exportOptions": {
    "_class": "exportOptions",
    "do_objectID": "40D6543E-EF53-4241-BA0E-4FFBDF394F89",
    "exportFormats": [
    ],
    "includedLayerIds": [
    ],
    "layerOptions": 0,
    "shouldTrim": false
  },
  "fixedRadius": 0,
  "frame": {
    "_class": "rect",
    "constrainProportions": false,
    "do_objectID": "2678DD52-0F48-4D78-AE1D-E410CDDE9B41",
    "height": 1024,
    "width": 1680,
    "x": 0,
    "y": 0
  },
  "hasClippingMask": false,
  "hasConvertedToNewRoundCorners": true,
  "isClosed": true,
  "isFixedToViewport": false,
  "isFlippedHorizontal": false,
  "isFlippedVertical": false,
  "isLocked": false,
  "isVisible": false,
  "layerListExpandedType": 1,
  "name": "hero-bgd-img-night-field",
  "nameIsFixed": true,
  "pointRadiusBehaviour": 1,
  "points": [
    {
      "_class": "curvePoint",
      "cornerRadius": 0,
      "curveFrom": "{0, 0}",
      "curveMode": 1,
      "curveTo": "{0, 0}",
      "hasCurveFrom": false,
      "hasCurveTo": false,
      "point": "{0, 0}"
    },
    {
      "_class": "curvePoint",
      "cornerRadius": 0,
      "curveFrom": "{1, 0}",
      "curveMode": 1,
      "curveTo": "{1, 0}",
      "hasCurveFrom": false,
      "hasCurveTo": false,
      "point": "{1, 0}"
    },
    {
      "_class": "curvePoint",
      "cornerRadius": 0,
      "curveFrom": "{1, 1}",
      "curveMode": 1,
      "curveTo": "{1, 1}",
      "hasCurveFrom": false,
      "hasCurveTo": false,
      "point": "{1, 1}"
    },
    {
      "_class": "curvePoint",
      "cornerRadius": 0,
      "curveFrom": "{0, 1}",
      "curveMode": 1,
      "curveTo": "{0, 1}",
      "hasCurveFrom": false,
      "hasCurveTo": false,
      "point": "{0, 1}"
    }
  ],
  "resizingConstraint": 63,
  "resizingType": 0,
  "rotation": 0,
  "shouldBreakMaskChain": false,
  "style": {
    "_class": "style",
    "borders": [
      {
        "_class": "border",
        "color": {
          "_class": "color",
          "alpha": 1,
          "blue": 0.592,
          "green": 0.592,
          "red": 0.592
        },
        "fillType": 0,
        "isEnabled": false,
        "position": 1,
        "thickness": 1
      }
    ],
    "do_objectID": "2812F6FA-9063-406B-9A0A-8BBD8663E414",
    "endMarkerType": 0,
    "fills": [
      {
        "_class": "fill",
        "color": {
          "_class": "color",
          "alpha": 0.1,
          "blue": 0,
          "green": 0,
          "red": 0
        },
        "fillType": 4,
        "image": {
          "_class": "MSJSONFileReference",
          "_ref": "images/d315d34de6320568882758b1cdefa440ef9e7e78.png",
          "_ref_class": "MSImageData"
        },
        "isEnabled": true,
        "noiseIndex": 0,
        "noiseIntensity": 0,
        "patternFillType": 1,
        "patternTileScale": 1
      }
    ],
    "miterLimit": 10,
    "startMarkerType": 0,
    "windingRule": 1
  },
  "userInfo": {
    "datasupplier.key": "unsplash_dataprovider_SupplyRandomPhoto",
    "unsplash": {
      "unsplash.photo.id": "\"fWIYXJGslEY\""
    }
  }
}