{
  "_class": "group",
  "booleanOperation": -1,
  "clippingMaskMode": 0,
  "do_objectID": "8AA53425-252B-46F8-80EB-5BA4AC6E66F0",
  "exportOptions": {
    "_class": "exportOptions",
    "do_objectID": "D5B3D068-7CA1-4B87-8B40-8427366A5723",
    "exportFormats": [
    ],
    "includedLayerIds": [
    ],
    "layerOptions": 0,
    "shouldTrim": false
  },
  "frame": {
    "_class": "rect",
    "constrainProportions": true,
    "do_objectID": "DA1A646B-88D3-4AEC-B2F6-B71044882F7C",
    "height": 48,
    "width": 48,
    "x": 109,
    "y": 399
  },
  "groupLayout": {
    "_class": "MSImmutableFreeformGroupLayout",
    "do_objectID": "BC32C2AB-9607-4A70-BB0C-7D264F95FF59"
  },
  "hasClickThrough": false,
  "hasClippingMask": false,
  "isFixedToViewport": false,
  "isFlippedHorizontal": false,
  "isFlippedVertical": false,
  "isLocked": false,
  "isVisible": true,
  "layerListExpandedType": 1,
  "layers": [
    {
      "class": "shapeGroup",
      "id": "3D659097-A20D-40EC-9C61-991082B1DD24"
    },
    {
      "class": "shapePath",
      "id": "D8CAD93D-60C2-4BC3-A5CB-D4292E1628C6"
    }
  ],
  "name": "baseline-search-24px",
  "nameIsFixed": false,
  "resizingConstraint": 63,
  "resizingType": 0,
  "rotation": 0,
  "shouldBreakMaskChain": false,
  "style": {
    "_class": "style",
    "do_objectID": "DE27BBE9-595A-409E-B864-53F364A050D9",
    "endMarkerType": 0,
    "miterLimit": 10,
    "startMarkerType": 0,
    "windingRule": 1
  }
}