{
  "_class": "artboard",
  "backgroundColor": {
    "_class": "color",
    "alpha": 1,
    "blue": 1,
    "green": 1,
    "red": 1
  },
  "booleanOperation": 0,
  "clippingMaskMode": 0,
  "do_objectID": "BC9685E3-2848-43AB-9AAF-A3E076DF22C3",
  "exportOptions": {
    "_class": "exportOptions",
    "exportFormats": [
    ],
    "includedLayerIds": [
    ],
    "layerOptions": 0,
    "shouldTrim": false
  },
  "frame": {
    "_class": "rect",
    "constrainProportions": false,
    "height": 3637,
    "width": 1200,
    "x": 19040,
    "y": 0
  },
  "grid": {
    "_class": "simpleGrid",
    "gridSize": 20,
    "isEnabled": false,
    "thickGridTimes": 10
  },
  "groupLayout": {
    "_class": "MSImmutableFreeformGroupLayout"
  },
  "hasBackgroundColor": false,
  "hasClickThrough": true,
  "hasClippingMask": false,
  "horizontalRulerData": {
    "_class": "rulerData",
    "base": 0,
    "guides": [
    ]
  },
  "includeBackgroundColorInExport": true,
  "includeInCloudUpload": true,
  "isFixedToViewport": false,
  "isFlippedHorizontal": false,
  "isFlippedVertical": false,
  "isFlowHome": false,
  "isLocked": false,
  "isVisible": true,
  "layerListExpandedType": 1,
  "layers": [
    {
      "class": "symbolInstance",
      "id": "1E355994-F6E3-49EB-9BB5-7176C0950989"
    },
    {
      "class": "group",
      "id": "9DAAFFB6-5002-4B09-B22D-2DE28A762BF8"
    },
    {
      "class": "group",
      "id": "6250869B-622C-4AAD-AD15-CD6B47676121"
    },
    {
      "class": "group",
      "id": "8898C575-AB55-48C1-9617-24F208DE3D49"
    },
    {
      "class": "symbolInstance",
      "id": "FE727ADF-AFC5-4994-919A-9386A89EECD2"
    },
    {
      "class": "group",
      "id": "B6949B29-E0A9-4A6E-B9F6-3CA07AD14ED3"
    }
  ],
  "layout": {
    "_class": "layoutGrid",
    "columnWidth": 70,
    "drawHorizontal": false,
    "drawHorizontalLines": false,
    "drawVertical": true,
    "gutterHeight": 12,
    "gutterWidth": 30,
    "guttersOutside": true,
    "horizontalOffset": 0,
    "isEnabled": true,
    "numberOfColumns": 12,
    "rowHeightMultiplication": 5,
    "totalWidth": 1200
  },
  "name": "02for-renters/02-education",
  "nameIsFixed": true,
  "resizesContent": false,
  "resizingConstraint": 63,
  "resizingType": 0,
  "rotation": 0,
  "shouldBreakMaskChain": true,
  "style": {
    "_class": "style",
    "endMarkerType": 0,
    "miterLimit": 10,
    "startMarkerType": 0,
    "windingRule": 1
  },
  "userInfo": {
    "com.animaapp.stc-sketch-plugin": {
      "kModelPropertiesKey": {
        "nestedSymbolsCacheKey": "k6yXHwW7lkJ8E6Bg4Qs3d9rgKz5ER82U/Uj9lDP5NtY="
      }
    }
  },
  "verticalRulerData": {
    "_class": "rulerData",
    "base": 0,
    "guides": [
    ]
  }
}