{
  "_class": "symbolInstance",
  "booleanOperation": 0,
  "clippingMaskMode": 0,
  "do_objectID": "8446B230-99BF-4687-94EA-89C4AC232542",
  "exportOptions": {
    "_class": "exportOptions",
    "exportFormats": [
    ],
    "includedLayerIds": [
    ],
    "layerOptions": 0,
    "shouldTrim": false
  },
  "frame": {
    "_class": "rect",
    "constrainProportions": false,
    "height": 16,
    "width": 587,
    "x": 230,
    "y": 248.2857142857147
  },
  "hasClippingMask": false,
  "horizontalSpacing": 0,
  "isFixedToViewport": false,
  "isFlippedHorizontal": false,
  "isFlippedVertical": false,
  "isLocked": false,
  "isVisible": true,
  "layerListExpandedType": 0,
  "name": "Progress/~50%",
  "nameIsFixed": false,
  "overrideValues": [
    {
      "_class": "overrideValue",
      "do_objectID": "D4C8C3B2-F623-4515-B540-76ECF153DF75",
      "overrideName": "AD9D45B8-740B-4EBC-807B-49C8F08B5508/959C8393-9EFB-41F0-BEA3-16FCD5ADA148_symbolID",
      "value": "E9FF8264-B06A-4F94-B0EC-92C08886556A"
    }
  ],
  "resizingConstraint": 63,
  "resizingType": 0,
  "rotation": 0,
  "scale": 1,
  "shouldBreakMaskChain": false,
  "style": {
    "_class": "style",
    "endMarkerType": 0,
    "miterLimit": 10,
    "startMarkerType": 0,
    "windingRule": 1
  },
  "symbolID": "556FD98D-CBDB-4BE3-866B-30379E865549",
  "verticalSpacing": 0
}