{
  "_class": "symbolInstance",
  "booleanOperation": -1,
  "clippingMaskMode": 0,
  "do_objectID": "A29AA564-D757-410C-9AB1-90DEAC2BEFE4",
  "exportOptions": {
    "_class": "exportOptions",
    "exportFormats": [
    ],
    "includedLayerIds": [
    ],
    "layerOptions": 0,
    "shouldTrim": false
  },
  "frame": {
    "_class": "rect",
    "constrainProportions": false,
    "height": 586,
    "width": 1200,
    "x": 0,
    "y": 4414
  },
  "hasClippingMask": false,
  "horizontalSpacing": 0,
  "isFixedToViewport": false,
  "isFlippedHorizontal": false,
  "isFlippedVertical": false,
  "isLocked": false,
  "isVisible": true,
  "layerListExpandedType": 1,
  "name": "Footer-New",
  "nameIsFixed": false,
  "overrideValues": [
  ],
  "resizingConstraint": 63,
  "resizingType": 0,
  "rotation": 0,
  "scale": 1,
  "shouldBreakMaskChain": false,
  "style": {
    "_class": "style",
    "endMarkerType": 0,
    "miterLimit": 10,
    "startMarkerType": 0,
    "windingRule": 1
  },
  "symbolID": "008265D3-23FA-4C77-A761-523A7853FF1E",
  "verticalSpacing": 0
}