{
  "_class": "group",
  "booleanOperation": 0,
  "clippingMaskMode": 0,
  "do_objectID": "5944C042-2A69-4873-A020-5326D285E31B",
  "exportOptions": {
    "_class": "exportOptions",
    "do_objectID": "AD300277-0E7C-47EE-9114-ACB2A3B37099",
    "exportFormats": [
    ],
    "includedLayerIds": [
    ],
    "layerOptions": 0,
    "shouldTrim": false
  },
  "frame": {
    "_class": "rect",
    "constrainProportions": false,
    "do_objectID": "2C051546-F90F-40F9-A464-7FAD83877124",
    "height": 204,
    "width": 157,
    "x": 855,
    "y": 498
  },
  "groupLayout": {
    "_class": "MSImmutableFreeformGroupLayout"
  },
  "hasClickThrough": false,
  "hasClippingMask": false,
  "isFixedToViewport": false,
  "isFlippedHorizontal": false,
  "isFlippedVertical": false,
  "isLocked": false,
  "isVisible": true,
  "layerListExpandedType": 2,
  "layers": [
    {
      "class": "text",
      "id": "BE14E54D-979E-4757-9959-2537C703238D"
    },
    {
      "class": "oval",
      "id": "BE7D971A-D468-4423-96B0-EC47DECF9070"
    }
  ],
  "name": "Info",
  "nameIsFixed": true,
  "resizingConstraint": 63,
  "resizingType": 0,
  "rotation": 0,
  "shouldBreakMaskChain": false,
  "style": {
    "_class": "style",
    "do_objectID": "30369C18-7C25-40A8-B8AE-C717BFB58A70",
    "endMarkerType": 0,
    "miterLimit": 10,
    "startMarkerType": 0,
    "windingRule": 1
  },
  "userInfo": {
    "com.animaapp.stc-sketch-plugin": {
      "kModelPropertiesKey": {
      }
    }
  }
}